{
  "id": "ttd/frontend-test",
  "org": "ttd",
  "title": {
    "nb": "frontend-test"
  },
  "dataTypes": [
    {
      "id": "default",
      "allowedContentTypes": [
        "application/xml"
      ],
      "appLogic": {},
      "taskId": "Task_1",
      "maxCount": 1,
      "minCount": 1
    },
    {
      "id": "ref-data-as-pdf",
      "allowedContentTypes": [
        "application/pdf"
      ],
      "maxCount": 0,
      "minCount": 0
    }
  ],
  "partyTypesAllowed": {
    "bankruptcyEstate": false,
    "organisation": false,
    "person": false,
    "subUnit": false
  },
  "autoDeleteOnProcessEnd": false,
  "created": "2021-02-06T15:18:12.2060944Z",
  "createdBy": "jeeva",
  "lastChanged": "2021-02-06T15:18:12.2062288Z",
  "lastChangedBy": "jeeva"
}